{
    "CPedFactory": {
        "FiveM_GameProcess.exe": {
            "1604": {
                "offset": "0x6AD596"
            },
            "2060": {
                "offset": "0x6AD596"
            },
            "2189": {
                "offset": "0x6AD596"
            },
            "2372": {
                "offset": "0x6AD596"
            },
            "2545": {
                "offset": "0x6AD596"
            },
            "2612": {
                "offset": "0x6AD596"
            },
            "2699": {
                "offset": "0x6AD596"
            },
            "2802": {
                "offset": "0x6AD596"
            },
            "2944": {
                "offset": "0x6AD596"
            },
            "3095": {
                "offset": "0x6AD596"
            },
            "3258": {
                "offset": "0x6AD596"
            },
            "3570": {
                "offset": "0x6AD596"
            }
        },
        "FiveM_b3407_GameProcess.exe": {
            "3407": {
                "offset": "0x6B511A"
            }
        }
    }
}